[
  {
    "id": "UUID-1",
    "age": "30",
    "name": "John Snow",
    "imageURL": "johnsnow",
    "question": "Do you regret not taking the throne?",
    "answer": "“Mine is definitely sneaking the late night snacks”",
    "uplaodedImages": ["johnandsword", "johnsnow", "johnsnow2", "johnsnow3", "johnsnow4"]
  },
  {
    "id": "UUID-2",
    "age": "27",
    "name": "Ygritte",
    "imageURL": "ygrites",
    "question": "What is there behind the walls?",
    "answer": "“Mine is definitely sneaking the late night snacks”",
    "uplaodedImages": ["y4", "ygrites", "y2", "y3", "y1"]
  },
  {
    "id": "UUID-3",
    "age": "28",
    "name": "Sansa Stark",
    "imageURL": "sansa",
    "question": "How is it to be from being a nervous to nerve breaking queen?",
    "answer": "“Mine is definitely sneaking the late night snacks”",
    "uplaodedImages": ["sansa", "s2", "s3", "s4", "s5"]
  },
  {
    "id": "UUID-4",
    "age": "24",
    "name": "Robb Stark",
    "imageURL": "robb",
    "question": "Why did you trust Wlader Frey",
    "answer": "“Mine is definitely sneaking the late night snacks”",
    "uplaodedImages": ["robb", "r2"]
  },
  {
    "id": "UUID-5",
    "age": "37",
    "name": "Margaeray",
    "imageURL": "margarey",
    "question": "What's Next?",
    "answer": "“Mine is definitely sneaking the late night snacks”",
    "uplaodedImages": ["m1", "m2", "m3"]
  }
]
